Advento-0.1.1.dist-info/DESCRIPTION.rst
Advento-0.1.1.dist-info/METADATA
Advento-0.1.1.dist-info/RECORD
Advento-0.1.1.dist-info/WHEEL
Advento-0.1.1.dist-info/metadata.json
Advento-0.1.1.dist-info/top_level.txt
src/__init__.py
src/advento_test.py
