Metadata-Version: 2.0
Name: Advento
Version: 0.1.1
Summary: Fisica para Jogoso FGA
Home-page: https://github.com/halevalente/Advento
Author: Vinicius Rodrigues
Author-email: vinifladf@gmail.com
License: MIT License
Keywords: Fis Jogos
Platform: UNKNOWN
